{"singlePage": [], "startSite": "", "filingNum": "", "onePageListNum": 15, "commentLabelColor": "#006b75", "yearColorList": ["#bc4c00", "#0969da", "#1f883d", "#A333D0"], "i18n": "CN", "themeMode": "manual", "dayTheme": "light", "nightTheme": "dark", "urlMode": "pinyin", "script": "", "style": "", "head": "", "indexScript": "", "indexStyle": "", "bottomText": "", "showPostSource": 1, "iconList": {}, "UTC": 8, "rssSplit": "sentence", "exlink": {}, "needComment": 1, "allHead": "", "title": "Blog Title", "subTitle": "Blog description", "avatarUrl": "https://github.githubassets.com/favicons/favicon.svg", "GMEEK_VERSION": "last", "postListJson": {"P1": {"htmlDir": "docs/post/huan-ying.html", "labels": ["duplicate"], "postTitle": "\u6b22\u8fce", "postUrl": "post/huan-ying.html", "postSourceUrl": "https://github.com/xiaoovo663/HuaiXixian-Web/issues/1", "commentNum": 0, "wordCount": 36, "description": "\u6b22\u8fce\u6765\u5230\u6000\u516e\u7ea4\u7684\u5b98\u7f51\ud83d\ude4f\n\n\u4f60\u53ef\u4ee5\u5728\u8fd9\u91cc\u4e0b\u8f7d\u6587\u4ef6\n\u4e5f\u53ef\u4ee5\u627e\u5230\u6211\u7684\u8054\u7cfb\u65b9\u5f0f\u54e6\u3002", "top": 0, "createdAt": 1752911659, "style": "", "script": "", "head": "", "ogImage": "https://github.githubassets.com/favicons/favicon.svg", "createdDate": "2025-07-19", "dateLabelColor": "#0969da"}}, "singeListJson": {}, "labelColorDict": {"bug": "#d73a4a", "documentation": "#0075ca", "duplicate": "#cfd3d7", "enhancement": "#a2eeef", "good first issue": "#7057ff", "help wanted": "#008672", "invalid": "#e4e669", "question": "#d876e3", "wontfix": "#ffffff"}, "displayTitle": "Blog Title", "faviconUrl": "https://github.githubassets.com/favicons/favicon.svg", "ogImage": "https://github.githubassets.com/favicons/favicon.svg", "primerCSS": "<link href='https://mirrors.sustech.edu.cn/cdnjs/ajax/libs/Primer/21.0.7/primer.css' rel='stylesheet' />", "homeUrl": "https://xiaoovo663.github.io/HuaiXixian-Web", "prevUrl": "disabled", "nextUrl": "disabled"}